staticviking/staticviking.py
staticviking2-0.0.3.dist-info/LICENSE.txt
staticviking2-0.0.3.dist-info/METADATA
staticviking2-0.0.3.dist-info/WHEEL
staticviking2-0.0.3.dist-info/entry_points.txt
staticviking2-0.0.3.dist-info/top_level.txt
staticviking2-0.0.3.dist-info/zip-safe
staticviking2-0.0.3.dist-info/RECORD
