Metadata-Version: 2.1
Name: staticviking2
Version: 0.0.3
Summary: Simplest static page engine for Developers
Home-page: https://martinbaun.com/blog/posts/staticviking-zeroconf-static-website-for-blogs-wikis/
Author: Martin Baun
Author-email: pypi@martinbaun.com
Keywords: blog,productivity,static site generator
Classifier: Programming Language :: Python :: 3
Classifier: License :: OSI Approved :: MIT License
Classifier: Operating System :: OS Independent
Requires-Python: >=3.8
License-File: LICENSE.txt
Requires-Dist: Jinja2 ==3.1.2
Requires-Dist: python-slugify ==7.0.0
Requires-Dist: python-frontmatter ==1.0.0
Requires-Dist: docopt ==0.6.2
Requires-Dist: Markdown ==3.4.1
Requires-Dist: htmlmin ==0.1.12
Requires-Dist: Pillow >=10
